{
  "$schema": "../../schemas/uc.schema.json",
  "id": "5.14.20",
  "title": "Varnish Pipe Session Bypass Trending",
  "criticality": "medium",
  "difficulty": "intermediate",
  "monitoringType": [
    "Performance",
    "Analytics"
  ],
  "splunkPillar": "Observability",
  "dataSources": "`index=proxy` `sourcetype=varnish:vsl` pipe transactions",
  "app": "Splunk Universal Forwarder, Splunk Connect for Syslog, or HTTP Event Collector; `props.conf`/`transforms.conf` for listed sourcetypes",
  "spl": "index=proxy sourcetype=\"varnish:vsl\"\n| regex _raw=\"(?i)VCL_pipe|Link\\s+pipe\"\n| bin _time span=5m\n| stats count as pipe_sess by host, _time",
  "description": "Unexpected pipe volume loads origin more than dashboards suggest.",
  "value": "Explains origin spikes during large uploads.",
  "implementation": "Pipe mode disables caching for those requests; watch WebSocket or upload paths.",
  "visualization": "Time series for rates and latency, top/dedup for hotspots, single-value alerts on health thresholds.",
  "cimModels": [
    "N/A"
  ],
  "references": [
    {
      "title": "Vendor documentation",
      "url": "https://varnish-cache.org/docs/trunk/users-guide/vcl-pipe.html"
    }
  ],
  "equipment": [
    "syslog",
    "varnish"
  ],
  "status": "draft",
  "lastReviewed": "2026-04-24",
  "splunkVersions": [
    "9.2+",
    "Cloud"
  ],
  "reviewer": "catalog-team",
  "grandmaExplanation": "We track requests that skip caching entirely."
}
