{
  "$schema": "https://json-schema.org/draft/2020-12/schema",
  "$id": "https://splunk-monitoring.io/schemas/v2/build-telemetry.schema.json",
  "title": "Per-stage build telemetry",
  "description": "Wall-clock timings emitted to dist/build-telemetry.json by tools/build/build.py once per non-reproducible build. Captures the elapsed milliseconds each pipeline stage took, in the order the pipeline executed them. Adding a new stage is non-breaking; renaming or removing the schema_version field is a major bump.",
  "version": "1.0.0",
  "x-stability": "stable",
  "x-since": "v9.x",
  "type": "object",
  "additionalProperties": false,
  "required": ["$schema", "schema_version", "build", "totals", "stages"],
  "properties": {
    "$schema": {
      "type": "string",
      "description": "Pointer to this schema so consumers can locate it without an out-of-band fetch."
    },
    "schema_version": {
      "type": "string",
      "pattern": "^\\d+\\.\\d+\\.\\d+$",
      "description": "Semver of the build-telemetry.json wire format."
    },
    "build": {
      "type": "object",
      "additionalProperties": false,
      "required": ["platform", "python"],
      "properties": {
        "platform": {
          "type": "string",
          "description": "Output of platform.platform(); coarse OS/arch identifier for cross-machine comparisons."
        },
        "python": {
          "type": "string",
          "pattern": "^\\d+\\.\\d+\\.\\d+$",
          "description": "Major.Minor.Micro of the Python interpreter that ran the build."
        }
      }
    },
    "totals": {
      "type": "object",
      "additionalProperties": false,
      "required": ["stages", "duration_ms"],
      "properties": {
        "stages": {
          "type": "integer",
          "minimum": 0,
          "description": "Number of stage records in the stages array."
        },
        "duration_ms": {
          "type": "integer",
          "minimum": 0,
          "description": "Total wall-clock build duration in milliseconds."
        }
      }
    },
    "stages": {
      "type": "array",
      "description": "Per-stage timing in pipeline-execution order. Empty when the build runs zero stages (e.g. --only with an empty list).",
      "items": {
        "type": "object",
        "required": ["stage", "duration_ms"],
        "properties": {
          "stage": {
            "type": "string",
            "minLength": 1,
            "description": "Pipeline stage name. Must be one of the canonical stages, but the schema does not enumerate them so a new stage can land without a same-PR schema bump."
          },
          "duration_ms": {
            "type": "integer",
            "minimum": 0,
            "description": "Wall-clock duration of this stage in milliseconds."
          }
        }
      }
    }
  }
}
