{
  "$schema": "../../schemas/uc.schema.json",
  "id": "17.1.47",
  "title": "Cisco ISE Backup Job Success and Operational-Data Backup Validation",
  "criticality": "high",
  "difficulty": "intermediate",
  "monitoringType": [
    "Compliance",
    "Operations"
  ],
  "splunkPillar": "IT Operations",
  "compliance": [
    {
      "regulation": "pci-dss",
      "version": "v4.0",
      "clause": "9.4.5",
      "mode": "satisfies",
      "assurance": "contributing",
      "assurance_rationale": "PCI 9.4.5 (sub-clause around media backup) requires backup-media handling controls. Backup-success monitoring evidences the operational integrity of backups for audit-relevant systems.",
      "controlObjective": "Operational integrity of audit-system backup.",
      "evidenceArtifact": "UC-17.1.47 alert log.",
      "obligationRef": "pci-dss@v4.0#9.4.5",
      "provenance": "maintainer"
    },
    {
      "regulation": "nis2",
      "version": "Directive (EU) 2022/2555",
      "clause": "Art.21(2)(c)",
      "mode": "satisfies",
      "assurance": "contributing",
      "assurance_rationale": "Art.21(2)(c) requires backup management. Backup-success monitoring is the primary control.",
      "controlObjective": "Backup management primary.",
      "evidenceArtifact": "UC-17.1.47 alert log + monthly backup attestation.",
      "obligationRef": "nis2@Directive (EU) 2022/2555#Art.21(2)(c)",
      "provenance": "maintainer",
      "clauseUrl": "https://eur-lex.europa.eu/eli/dir/2022/2555/oj"
    },
    {
      "regulation": "dora",
      "version": "Regulation (EU) 2022/2554",
      "clause": "Art.12",
      "mode": "satisfies",
      "assurance": "contributing",
      "assurance_rationale": "Art.12 (Backup policies and recovery procedures) — direct alignment.",
      "controlObjective": "Backup policy fulfilment.",
      "evidenceArtifact": "UC-17.1.47 alert log.",
      "obligationRef": "dora@Regulation (EU) 2022/2554#Art.12",
      "provenance": "maintainer"
    },
    {
      "regulation": "nist-800-53",
      "version": "Rev. 5",
      "clause": "CP-9",
      "mode": "satisfies",
      "assurance": "contributing",
      "assurance_rationale": "CP-9 (System Backup) — direct alignment.",
      "controlObjective": "System backup primary.",
      "evidenceArtifact": "UC-17.1.47 alert log.",
      "obligationRef": "nist-800-53@Rev. 5#CP-9",
      "provenance": "maintainer"
    },
    {
      "regulation": "iso-27001",
      "version": "2022",
      "clause": "A.8.13",
      "mode": "satisfies",
      "assurance": "contributing",
      "assurance_rationale": "A.8.13 (Information backup) — direct alignment.",
      "controlObjective": "Information backup primary.",
      "evidenceArtifact": "UC-17.1.47 alert log.",
      "obligationRef": "iso-27001@2022#A.8.13",
      "provenance": "maintainer"
    },
    {
      "regulation": "soc-2",
      "version": "2017 TSC",
      "clause": "A1.2",
      "mode": "satisfies",
      "assurance": "contributing",
      "assurance_rationale": "A1.2 — backup is a primary availability input.",
      "controlObjective": "Availability backup.",
      "evidenceArtifact": "UC-17.1.47 alert log.",
      "obligationRef": "soc-2@2017 TSC#A1.2",
      "provenance": "maintainer"
    },
    {
      "regulation": "hipaa-security",
      "version": "2013-final",
      "clause": "§164.308(a)(7)",
      "mode": "satisfies",
      "assurance": "contributing",
      "assurance_rationale": "164.308(a)(7) Contingency Plan — backup is a primary requirement.",
      "controlObjective": "Contingency-plan backup.",
      "evidenceArtifact": "UC-17.1.47 alert log.",
      "obligationRef": "hipaa-security@45 CFR Parts 160, 162, 164#§164.308(a)(7)",
      "provenance": "maintainer"
    }
  ],
  "controlTest": {
    "positiveScenario": "Misconfigure backup repository credentials. Run a manual backup. ISE emits 51032 (failed). UC-17.1.47 fires showing the (backup_type, repository) with failures > 0.",
    "negativeScenario": "Fix credentials. Successful backup emits 51031. Alert clears on next 4h schedule."
  },
  "dataSources": "ISE syslog `index=nac sourcetype=cisco:ise:syslog` *Administrative and Operational Audit* category — backup codes `51030` (backup operation started), `51031` (backup completed successfully), `51032` (backup failed), `51033` (backup partial — some data could not be backed up), `51034` (backup repository validation failed), `51035` (operational-data backup completed). Fields: `backup_type` (config|operational|standalone), `backup_repository`, `backup_size_mb`, `triggered_by` (admin|scheduled). ISE OpenAPI `/api/v1/backup/status` polled every 1h, written to `index=nac sourcetype=cisco:ise:backup_status`.",
  "app": "`Splunk Add-on for Cisco Identity Services` ([Splunkbase 1915](https://splunkbase.splunk.com/app/1915)).",
  "spl": "(index=nac sourcetype=\"cisco:ise:syslog\" MessageCode IN (51030, 51031, 51032, 51033, 51034, 51035))\n  OR (index=nac sourcetype=\"cisco:ise:backup_status\")\n| eval status = case(MessageCode==\"51031\" OR MessageCode==\"51035\", \"success\", MessageCode IN (\"51032\",\"51033\",\"51034\"), \"failure\", MessageCode==\"51030\", \"started\", true(), \"snapshot\")\n| stats count latest(_time) as last_run, count(eval(status==\"success\")) as successes count(eval(status==\"failure\")) as failures latest(backup_size_mb) as size_mb by backup_type, backup_repository\n| eval days_since_success = round((now() - last_run) / 86400, 1)\n| where failures > 0 OR (status==\"snapshot\" AND days_since_success > 2) OR successes==0",
  "description": "Detects ISE backup-job failures, missed scheduled backups (>48h without a successful backup), and degraded backups (partial / repository validation failures). Covers config backup AND operational-data backup as separate streams.",
  "value": "ISE recovery requires a recent backup. Without a recent valid backup, restoration after PAN failure rebuilds the deployment from the last available, possibly weeks-old, backup — losing all policy work since. Auditing backup health is the primary control for ISE disaster-recovery readiness. Operational-data backup is required for forensic continuity of MnT events; missing this backup means audit data is gone if the MnT node fails.",
  "implementation": "Confirm *Administrative and Operational Audit* category at INFO. Deploy OpenAPI poller every 1h. Schedule the search every 4h, search window `-12h@h to @h`, trigger on count > 0, throttle suppression on `backup_type` for 12h.",
  "visualization": "(1) Single value: days since last successful backup per type. (2) Calendar view: 90-day backup success/failure grid. (3) Top-N: most-failed repositories.",
  "cimModels": [
    "Change"
  ],
  "dataModelAcceleration": "Optional.",
  "references": [
    {
      "title": "Cisco ISE 3.4 Admin Guide — Backup and Restore",
      "url": "https://www.cisco.com/c/en/us/"
    }
  ],
  "knownFalsePositives": "(a) **First-backup-after-deployment** — Initial backup may take significantly longer than steady-state; suppress for 24h after first scheduled run. (b) **Repository network outage** — A NAS/SFTP outage causes 51034 (repository validation failed); cross-reference network maintenance. (c) **Partial backup during low-disk** — When MnT disk fills, operational-data backup falls back to partial. Cross-ref UC-17.1.29.",
  "mitreAttack": [
    "N/A (platform lifecycle — ISE backup status monitoring, no adversary technique)"
  ],
  "equipment": [
    "cisco",
    "syslog"
  ],
  "equipmentModels": [
    "cisco_ise"
  ],
  "status": "verified",
  "lastReviewed": "2026-05-06",
  "splunkVersions": [
    "9.2+",
    "Cloud"
  ],
  "reviewer": "@splunk-monitoring-use-cases",
  "detailedImplementation": "Prerequisites\n• Backup repository configured (Administration > Maintenance > Repository).\n• Scheduled backup configured (Administration > Maintenance > Backup & Restore > Schedule Backup).\n• `backup_repos.csv` lookup with `repository`, `criticality`.\n\nStep 1 — Configure data collection\nEnable *Administrative and Operational Audit* category at INFO.\n\nStep 2 — Create the search\nSearch in `spl` field. Schedule every 4h.\n\nStep 3 — Validate\nProvoke as above. Confirm fire.\n\nStep 4 — Operationalize\nDashboard \"ISE — Backup Health\":\n• Days-since-success per backup_type tile.\n• 90-day calendar view.\n• Repository top-N failures.\n\nMonthly attestation: ISE platform team signs off on backup success report.\n\nStep 5 — Troubleshooting\n• **Repository auth failure** — Re-store credential.\n• **Backup partial — operational data missing** — MnT disk full, cross-ref UC-17.1.29.\n• **Schedule never fires** — Schedule disabled in UI.",
  "grandmaExplanation": "We make sure ISE's safety copy (the backup) actually completes every day. If the backup fails or skips a day, we ring the bell — without a recent backup, we couldn't restore ISE if something went wrong.",
  "wave": "crawl"
}
